whisper_cli/__init__.py
whisper_cli/api.py
whisper_cli/cli.py
whisper_cli/utils.py
whisper_chat-1.0.6.dist-info/METADATA
whisper_chat-1.0.6.dist-info/WHEEL
whisper_chat-1.0.6.dist-info/entry_points.txt
whisper_chat-1.0.6.dist-info/top_level.txt
whisper_chat-1.0.6.dist-info/RECORD
